beamlit/__init__.py
beamlit/client.py
beamlit/errors.py
beamlit/py.typed
beamlit/types.py
beamlit/api/__init__.py
beamlit/api/agents/__init__.py
beamlit/api/agents/create_agent.py
beamlit/api/agents/create_agent_release.py
beamlit/api/agents/delete_agent.py
beamlit/api/agents/delete_agent_deployment.py
beamlit/api/agents/delete_agent_deployment_history.py
beamlit/api/agents/get_agent.py
beamlit/api/agents/get_agent_deployment.py
beamlit/api/agents/get_agent_deployment_history.py
beamlit/api/agents/get_agent_deployment_logs.py
beamlit/api/agents/get_agent_deployment_metrics.py
beamlit/api/agents/get_agent_metrics.py
beamlit/api/agents/list_agent_deployment_history.py
beamlit/api/agents/list_agent_deployments.py
beamlit/api/agents/list_agents.py
beamlit/api/agents/put_agent_deployment.py
beamlit/api/agents/put_agent_deployment_history.py
beamlit/api/agents/update_agent.py
beamlit/api/authentication_providers/__init__.py
beamlit/api/authentication_providers/get_model_with_repo_for_authentication_provider.py
beamlit/api/authentication_providers/list_models_for_authentication_provider.py
beamlit/api/authentication_providers/list_organizations_for_authentication_provider.py
beamlit/api/configurations/__init__.py
beamlit/api/configurations/get_configuration.py
beamlit/api/environments/__init__.py
beamlit/api/environments/create_environment.py
beamlit/api/environments/delete_environment.py
beamlit/api/environments/get_environment.py
beamlit/api/environments/get_environment_metrics.py
beamlit/api/environments/list_environments.py
beamlit/api/environments/update_environment.py
beamlit/api/functions/__init__.py
beamlit/api/functions/create_function.py
beamlit/api/functions/create_function_release.py
beamlit/api/functions/delete_function.py
beamlit/api/functions/delete_function_deployment.py
beamlit/api/functions/get_function.py
beamlit/api/functions/get_function_deployment.py
beamlit/api/functions/get_function_deployment_logs.py
beamlit-0.1.0.dist-info/METADATA
beamlit-0.1.0.dist-info/WHEEL
beamlit-0.1.0.dist-info/RECORD
