Metadata-Version: 2.3
Name: beamlit
Version: 0.1.0
Summary: Add your description here
Author-email: cploujoux <ch.ploujoux@gmail.com>
Requires-Python: >=3.12
Requires-Dist: attrs>=21.3.0
Requires-Dist: httpx<0.28.0,>=0.20.0
Requires-Dist: python-dateutil>=2.8.0
Requires-Dist: pyyaml==6.0.2
